{
  "date": "2020, puzzle 12",
  "title": "Rain Risk",
  "url": "https://adventofcode.com/2020/day/12",
  "input": "N2\nF85\nL90\nW5\nR90\nF56\nF16\nF98\nW4\nS3\nF92\nN3\nW2\nN3\nE2\nS4\nW1\nN2\nF7\nN2\nE3\nS1\nL90\nN2\nE2\nF13\nE5\nS4\nR90\nN2\nW4\nF55\nW3\nN1\nF93\nL90\nN3\nF72\nE4\nW1\nN2\nF76\nS5\nL90\nF44\nN2\nF81\nS1\nF28\nR270\nE5\nN4\nE5\nF23\nR270\nF53\nN2\nL90\nE5\nR180\nN1\nF99\nN3\nE2\nR180\nW5\nF70\nW5\nR180\nF9\nS1\nR90\nS1\nF58\nN3\nN4\nR180\nN3\nR90\nS5\nF6\nE3\nN4\nF38\nW4\nR180\nF53\nR180\nE2\nR90\nW4\nL180\nF13\nN3\nF80\nW1\nR270\nE2\nS1\nF24\nE5\nF1\nS3\nF34\nR90\nF54\nE4\nF59\nE4\nR180\nF88\nR90\nS1\nR90\nF6\nR90\nN1\nF89\nW3\nF9\nL180\nW1\nF47\nR180\nN2\nW1\nF28\nF73\nS1\nF27\nE2\nF82\nW3\nF38\nE4\nL90\nE4\nF64\nW5\nW3\nS2\nL180\nF22\nL90\nF10\nL90\nF64\nE4\nN4\nF21\nS4\nE3\nN5\nF71\nN3\nF93\nN2\nR90\nE4\nF64\nE1\nL90\nF37\nE5\nF96\nW2\nN4\nE2\nR90\nS1\nR90\nW1\nR180\nE2\nS2\nR90\nW3\nS2\nF94\nW2\nL180\nS2\nE4\nF54\nN2\nE4\nS3\nL180\nW2\nN1\nW2\nR90\nF54\nL180\nN2\nF87\nE2\nF23\nW3\nR180\nW4\nS3\nF93\nE5\nR90\nN4\nR90\nS4\nE3\nS3\nF31\nR90\nF89\nE3\nF73\nS5\nF97\nW1\nL180\nF52\nE3\nF68\nR90\nS2\nS5\nF26\nL180\nF12\nE2\nF83\nF9\nN2\nR90\nF99\nR90\nS4\nE5\nR90\nS4\nF84\nW4\nE5\nR90\nF42\nW4\nF94\nW1\nR270\nS3\nE5\nF23\nF38\nW2\nW1\nN5\nE2\nL180\nN1\nF26\nL90\nF5\nR90\nN5\nR180\nF25\nL90\nS1\nN3\nF62\nS1\nF77\nN3\nE3\nL90\nF93\nW3\nE3\nN2\nF14\nN5\nF80\nS2\nL90\nN4\nW2\nL180\nF81\nR180\nN4\nF8\nW4\nS4\nR90\nF34\nW2\nL180\nF49\nS4\nE4\nR90\nW2\nF75\nR90\nS5\nE4\nL90\nN3\nW4\nR90\nN4\nE3\nF62\nR90\nE4\nN2\nW3\nN1\nR90\nF75\nE1\nL180\nS3\nW1\nN2\nW5\nN3\nF70\nL90\nW1\nS2\nL270\nE5\nF21\nS3\nW3\nR90\nF3\nN3\nF85\nE5\nR90\nF8\nW2\nS3\nW4\nF38\nN5\nF54\nL90\nW3\nR90\nE5\nF2\nS5\nF79\nN4\nE2\nR180\nW2\nN1\nR90\nF57\nW4\nS1\nF27\nE5\nF31\nR90\nF11\nS5\nW4\nN3\nW1\nS1\nF93\nN3\nL180\nE1\nF63\nE2\nR180\nF99\nN3\nE3\nN3\nW5\nF66\nE5\nR90\nS1\nL90\nN1\nR90\nW5\nR90\nL90\nE4\nR270\nW3\nN5\nR90\nS5\nF8\nF93\nE3\nN4\nF48\nW1\nR180\nN1\nR90\nW3\nR180\nF3\nR180\nF8\nN4\nE1\nF34\nN1\nF33\nN4\nR90\nL180\nE3\nF35\nS5\nF64\nL90\nE4\nF30\nR90\nL90\nE5\nN4\nR180\nS2\nW3\nR90\nF35\nL180\nE2\nS3\nE5\nL90\nN5\nR90\nR90\nN4\nE5\nF34\nW5\nW4\nL90\nE2\nN2\nS5\nF85\nS5\nF98\nW1\nS3\nF7\nE2\nS4\nF27\nL180\nF30\nL90\nW1\nF87\nW1\nE2\nE2\nN3\nF64\nE4\nF31\nL270\nS3\nW2\nF60\nS2\nE1\nL180\nF2\nW3\nS3\nE3\nR180\nF12\nL180\nE1\nR90\nL180\nF60\nR90\nE4\nR180\nE3\nS1\nE3\nS1\nF86\nR90\nE1\nS4\nF47\nN4\nE4\nN4\nW4\nR90\nS3\nF81\nS1\nE1\nL270\nS2\nL90\nE5\nF62\nW4\nF78\nL90\nF18\nS5\nR180\nS1\nR270\nS3\nW5\nF3\nN1\nR90\nN4\nF59\nN1\nW4\nR90\nE3\nN3\nN4\nL90\nW5\nS2\nL90\nN2\nW1\nL180\nF49\nN4\nF14\nL180\nN2\nF43\nS3\nF84\nE3\nR180\nS4\nW1\nF90\nF58\nW3\nF18\nE5\nL90\nF72\nW1\nN1\nR90\nS3\nF79\nE4\nS4\nF31\nN4\nF66\nL90\nW1\nN2\nE4\nF74\nW1\nN2\nE5\nS5\nL90\nE3\nF71\nN3\nR90\nN4\nE2\nN2\nF83\nL90\nW4\nF64\nL90\nW1\nS2\nE4\nF48\nS3\nW5\nL90\nE5\nS1\nL180\nE4\nN4\nF40\nE4\nR270\nF85\nE4\nR90\nL90\nS1\nR270\nW1\nR180\nF72\nS2\nR90\nF63\nR180\nF93\nE4\nS4\nR90\nW3\nR90\nF10\nE4\nF93\nR180\nE1\nE3\nR90\nW1\nL180\nF83\nW4\nF41\nW4\nR90\nF1\nL90\nW4\nL90\nN4\nR180\nS5\nF63\nS2\nE4\nR90\nF90\nE5\nS2\nL90\nF64\nR90\nL90\nN1\nE4\nF20\nW3\nN4\nR90\nW5\nN1\nE5\nW4\nR90\nN1\nF72\nS5\nF78\nS2\nR180\nN4\nL180\nN5\nF22\nW4\nR180\nF19\nW3\nL90\nE4\nF27\nW5\nS4\nE4\nF34\nN4\nF40\nN3\nR90\nL90\nS2\nW1\nR90\nE3\nR90\nN1\nW4\nF93\nN5\nL90\nF7\nE1\nL90\nW4\nN3\nE5\nF62\nR90\nW4\nL90\nS3\nE4\nL270\nS3\nW5\nS2\nF30\nN2\nF70\nS5\nW1\nS3\nR90\nE4\nS5\nL90\nS2\nR90\nW1\nL90\nW5\nF8\nR90\nN4\nL180\nN5\nL90\nN3\nF30\nW2\nF39\nE3\nF17\nW3\nS1\nF48\nE1\nR90\nF35\nW2\nL180\nS1\nL90\nE5\nS1\nR90\nE2\nS5\nW2\nN1\nE3\nF100\nS2\nE4\nL90\nW5\nR90\nF81\nS4\nR90\nF80",
  "part1": {
    "examples": [
      {
        "input": "F10\nN3\nF7\nR90\nF11",
        "answer": "25"
      }
    ],
    "answer": "2280"
  },
  "part2": {
    "examples": [
      {
        "input": "F10\nN3\nF7\nR90\nF11",
        "answer": "286"
      }
    ],
    "answer": "38693"
  }
}